MANIFEST.in
README.rst
setup.py
src/yota/__init__.py
src/yota/exceptions.py
src/yota/nodes.py
src/yota/processors.py
src/yota/renderers.py
src/yota/validators.py
src/yota.egg-info/PKG-INFO
src/yota.egg-info/SOURCES.txt
src/yota.egg-info/dependency_links.txt
src/yota.egg-info/requires.txt
src/yota.egg-info/top_level.txt
src/yota/js/yota.js
src/yota/templates/jinja/button.html
src/yota/templates/jinja/captcha.html
src/yota/templates/jinja/checkbox.html
src/yota/templates/jinja/checkbox_group.html
src/yota/templates/jinja/entry.html
src/yota/templates/jinja/file.html
src/yota/templates/jinja/form_close.html
src/yota/templates/jinja/form_open.html
src/yota/templates/jinja/horiz.html
src/yota/templates/jinja/inline.html
src/yota/templates/jinja/list.html
src/yota/templates/jinja/password.html
src/yota/templates/jinja/radio_group.html
src/yota/templates/jinja/submit.html
src/yota/templates/jinja/textarea.html