Metadata-Version: 1.1
Name: yota
Version: 0.2.2
Summary: A form library with a focus on simplicity
Home-page: https://github.com/icook/yota
Author: Isaac Cook
Author-email: yota-discuss@googlegroups.com
License: LICENSE
Platform: UNKNOWN
Classifier: Intended Audience :: Developers
Classifier: Programming Language :: Python
Classifier: Programming Language :: Python :: 2.6
Classifier: Programming Language :: Python :: 2.7
Classifier: Programming Language :: Python :: Implementation :: CPython
